openai_toolgen/__init__.py
openai_toolgen/toolbox.py
openai_toolgen-0.3.1.dist-info/LICENSE
openai_toolgen-0.3.1.dist-info/METADATA
openai_toolgen-0.3.1.dist-info/WHEEL
openai_toolgen-0.3.1.dist-info/top_level.txt
openai_toolgen-0.3.1.dist-info/RECORD
