Metadata-Version: 2.1
Name: openai-toolgen
Version: 0.3.1
Summary: A library for generating tools for OpenAI projects
Home-page: https://github.com/visendi-labs/openai-toolgen
Author: Rasmus Nordström
Author-email: nordstrom.rasmus@gmail.com
Classifier: Programming Language :: Python :: 3
Classifier: License :: OSI Approved :: MIT License
Classifier: Operating System :: OS Independent
Requires-Python: >=3.6
License-File: LICENSE
